saltext/vmware/__init__.py
saltext/vmware/loader.py
saltext/vmware/version.py
saltext/vmware/config/schemas/esxcluster.py
saltext/vmware/config/schemas/esxdatacenter.py
saltext/vmware/config/schemas/esxi.py
saltext/vmware/config/schemas/esxvm.py
saltext/vmware/config/schemas/vcenter.py
saltext/vmware/grains/esxi.py
saltext/vmware/modules/cluster.py
saltext/vmware/modules/cluster_drs.py
saltext/vmware/modules/cluster_ha.py
saltext/vmware/modules/datacenter.py
saltext/vmware/modules/datastore.py
saltext/vmware/modules/dvportgroup.py
saltext/vmware/modules/dvswitch.py
saltext/vmware/modules/esxi.py
saltext/vmware/modules/folder.py
saltext/vmware/modules/license_mgr.py
saltext/vmware/modules/nsxt_compute_manager.py
saltext/vmware/modules/nsxt_ip_blocks.py
saltext/vmware/modules/nsxt_ip_pools.py
saltext/vmware/modules/nsxt_license.py
saltext/vmware/modules/nsxt_manager.py
saltext/vmware/modules/nsxt_policy_segment.py
saltext/vmware/modules/nsxt_policy_tier0.py
saltext/vmware/modules/nsxt_policy_tier1.py
saltext/vmware/modules/nsxt_transport_node.py
saltext/vmware/modules/nsxt_transport_node_profiles.py
saltext/vmware/modules/nsxt_transport_zone.py
saltext/vmware/modules/nsxt_uplink_profiles.py
saltext/vmware/modules/ssl_adapter.py
saltext/vmware/modules/storage_policies.py
saltext/vmware/modules/tag.py
saltext/vmware/modules/vm.py
saltext/vmware/modules/vmc_dhcp_profiles.py
saltext/vmware/modules/vmc_direct_connect.py
saltext/vmware/modules/vmc_distributed_firewall_rules.py
saltext/vmware/modules/vmc_dns_forwarder.py
saltext/vmware/modules/vmc_nat_rules.py
saltext/vmware/modules/vmc_networks.py
saltext/vmware/modules/vmc_org_users.py
saltext/vmware/modules/vmc_public_ip.py
saltext/vmware/modules/vmc_sddc.py
saltext/vmware/modules/vmc_sddc_clusters.py
saltext/vmware/modules/vmc_sddc_host.py
saltext/vmware/modules/vmc_security_groups.py
saltext/vmware/modules/vmc_security_rules.py
saltext/vmware/modules/vmc_vcenter_stats.py
saltext/vmware/modules/vmc_vm_disks.py
oms_saltext_vmware-25.1.8.post2.dist-info/LICENSE
oms_saltext_vmware-25.1.8.post2.dist-info/METADATA
oms_saltext_vmware-25.1.8.post2.dist-info/NOTICE.txt
oms_saltext_vmware-25.1.8.post2.dist-info/WHEEL
oms_saltext_vmware-25.1.8.post2.dist-info/entry_points.txt
oms_saltext_vmware-25.1.8.post2.dist-info/top_level.txt
oms_saltext_vmware-25.1.8.post2.dist-info/RECORD
