Metadata-Version: 2.1
Name: oms-saltext-vmware
Version: 25.1.8.post2
Summary: Salt Extension Modules for VMware
Home-page: https://docs.saltproject.io/salt/extensions/salt-ext-modules-vmware/en/latest/index.html
Author: VMware, Inc.
Author-email: joey@vmware.com
Maintainer: Joey Gibson
Maintainer-email: joey@vmware.com
License: Apache Software License
Project-URL: Source, https://github.com/saltstack/salt-ext-modules-vmware
Project-URL: Tracker, https://github.com/saltstack/salt-ext-modules-vmware/issues
Keywords: salt-extension
Platform: any
Classifier: Programming Language :: Python
Classifier: Programming Language :: Cython
Classifier: Programming Language :: Python :: 3
Classifier: Programming Language :: Python :: 3 :: Only
Classifier: Programming Language :: Python :: 3.7
Classifier: Programming Language :: Python :: 3.8
Classifier: Programming Language :: Python :: 3.9
Classifier: Programming Language :: Python :: 3.10
Classifier: Development Status :: 4 - Beta
Classifier: Intended Audience :: Developers
Classifier: License :: OSI Approved :: Apache Software License
Requires-Python: >=3.7
License-File: LICENSE
License-File: NOTICE.txt
Requires-Dist: salt>=3006
Requires-Dist: pyvmomi==7.0.3
Requires-Dist: importlib_metadata; python_version < "3.8"
Requires-Dist: jinja2>=3.1.0
Provides-Extra: tests
Requires-Dist: pytest>=6.1.0; extra == "tests"
Requires-Dist: pytest-cov; extra == "tests"
Requires-Dist: pytest-salt-factories>=1.0.0rc27; extra == "tests"
Provides-Extra: dev
Requires-Dist: nox; extra == "dev"
Requires-Dist: towncrier==21.9.0rc1; extra == "dev"
Provides-Extra: release
Requires-Dist: twine; extra == "release"
Requires-Dist: wheel; extra == "release"
Requires-Dist: towncrier==21.9.0rc1; extra == "release"
Provides-Extra: docs
Requires-Dist: sphinx; extra == "docs"
Requires-Dist: furo; extra == "docs"
Requires-Dist: sphinx-prompt; extra == "docs"
Requires-Dist: sphinxcontrib-spelling; extra == "docs"
Requires-Dist: importlib_metadata; python_version < "3.8" and extra == "docs"
Requires-Dist: towncrier==21.9.0rc1; extra == "docs"
